hpdata/__init__.py
hpdata/orchestration_utils.py
hpdata-0.0.9.dist-info/METADATA
hpdata-0.0.9.dist-info/WHEEL
hpdata-0.0.9.dist-info/top_level.txt
hpdata-0.0.9.dist-info/RECORD
