Metadata-Version: 2.4
Name: hpdata
Version: 0.0.9
Summary: Data Product Sq Utils
Home-page: https://github.com/healingpaper/vegas-workflow
Author: Data Product Sq
Author-email: sid.jang@healingpaper.com
Requires-Dist: snowflake-sqlalchemy<2.0,>=1.1.10
Requires-Dist: snowflake-connector-python[pandas]>=2.7.8
Requires-Dist: pandas>=0.25.3
Requires-Dist: pyyaml<=6.0.2,>=6.0.0
Requires-Dist: pygsheets>=2.0.5
Dynamic: author
Dynamic: author-email
Dynamic: description
Dynamic: description-content-type
Dynamic: home-page
Dynamic: requires-dist
Dynamic: summary
